ztimer.py
ztimer-1.0.5.dist-info/METADATA
ztimer-1.0.5.dist-info/RECORD
ztimer-1.0.5.dist-info/WHEEL
ztimer-1.0.5.dist-info/top_level.txt
