Metadata-Version: 2.1
Name: ztimer
Version: 1.0.5
Summary: 计时器池管理器, 将多个计时器挂在到计时器管理器中, 用一个线程来统一管理, 减少资源消耗
Home-page: https://pypi.org/
Author: zlyuan
Author-email: 1277260932@qq.com
License: GNU GENERAL PUBLIC LICENSE
Platform: all
Classifier: Environment :: Web Environment
Classifier: Intended Audience :: Developers
Classifier: Operating System :: OS Independent
Classifier: Programming Language :: Python
Classifier: Programming Language :: Python :: 3
Classifier: Programming Language :: Python :: 3.5
Classifier: Programming Language :: Python :: 3.6
Requires-Dist: zsingleton
Requires-Dist: zblocker (>=1.0.2)
